promplate_inspect-0.0.2.2.dist-info/METADATA
promplate_inspect-0.0.2.2.dist-info/WHEEL
promplate_inspect.py
promplate_inspect-0.0.2.2.dist-info/RECORD
