Metadata-Version: 2.1
Name: promplate-inspect
Version: 0.0.2.2
Summary: [WIP] Inspect a promplate.Template to get its signatures
Author-Email: Muspi Merol <me@promplate.dev>
License: MIT
Requires-Python: >=3.8
Requires-Dist: promplate<0.4,>=0.3.3.1.post1
